lndb_hub/__init__.py
lndb_hub/_entities.py
lndb_hub/_hub.py
lndb_hub/_schema.py
lndb_hub-0.6.1.dist-info/LICENSE
lndb_hub-0.6.1.dist-info/WHEEL
lndb_hub-0.6.1.dist-info/METADATA
lndb_hub-0.6.1.dist-info/RECORD
