Metadata-Version: 2.1
Name: lndb_hub
Version: 0.6.1
Summary: Connect to the hub from LaminDB.
Author-email: Lamin Labs <laminlabs@gmail.com>
Requires-Dist: lamin_logger
Requires-Dist: lndb_setup==0.12.2
Requires-Dist: lnschema_core==0.14.0
Requires-Dist: lnschema_wetlab==0.7.2
Requires-Dist: lnschema_bionty==0.4.3
Requires-Dist: lnbfx==0.4.5
Requires-Dist: pre-commit ; extra == "dev"
Requires-Dist: nox ; extra == "dev"
Requires-Dist: pytest>=6.0 ; extra == "test"
Requires-Dist: pytest-cov ; extra == "test"
Project-URL: Home, https://github.com/laminlabs/lndb-hub
Provides-Extra: dev
Provides-Extra: test
